sc_cc_ng_models_python/__init__.py
sc_cc_ng_models_python-0.1.15.dist-info/METADATA
sc_cc_ng_models_python-0.1.15.dist-info/WHEEL
sc_cc_ng_models_python-0.1.15.dist-info/RECORD
