Metadata-Version: 2.1
Name: sc-cc-ng-models-python
Version: 0.1.15
Summary: 
Author: Rikard Olsson
Author-email: rikard@thryselius.se
Requires-Python: >=3.9,<4.0
Classifier: Programming Language :: Python :: 3
Classifier: Programming Language :: Python :: 3.9
Classifier: Programming Language :: Python :: 3.10
Classifier: Programming Language :: Python :: 3.11
Classifier: Programming Language :: Python :: 3.12
